opp_perch-0.16.3.dist-info/DESCRIPTION.rst
opp_perch-0.16.3.dist-info/METADATA
opp_perch-0.16.3.dist-info/RECORD
opp_perch-0.16.3.dist-info/WHEEL
opp_perch-0.16.3.dist-info/entry_points.txt
opp_perch-0.16.3.dist-info/metadata.json
opp_perch-0.16.3.dist-info/top_level.txt
perch/__init__.py
perch/cli.py
perch/exceptions.py
perch/migrate.py
perch/model.py
perch/organisation.py
perch/user.py
perch/validators.py
perch/views.py
perch/migrations/__init__.py
perch/migrations/user_22e76f4ff8bd41e19aa52839fc8f13a1.py
