Metadata-Version: 2.0
Name: opp-perch
Version: 0.16.3
Summary: Open Permissions Platform Couchdb Library
Home-page: https://github.com/openpermissions/perch
Author: Open Permissions Platform Coalition
Author-email: support@openpermissions.org
License: UNKNOWN
Platform: UNKNOWN
Requires-Dist: click
Requires-Dist: enum34 (==1.0.4)
Requires-Dist: passlib (==1.6.2)
Requires-Dist: python-dateutil (==2.5.2)
Requires-Dist: tornado-couchdb (==0.2.3)
Requires-Dist: voluptuous (==0.8.9)
